Gate_VHDL/full_sub/full_sub.vhdl
library IEEE;
use IEEE.std_logic_1164.all;

entity full_sub  is 
port (
        a,b,bin: in std_logic;
        diff,bo: out std_logic
);
end full_sub;

architecture behavioral of full_sub is
begin
diff <= a xor b xor bin;
bo <= ((not a) and b) or (((not a) or bin) and b); 
end behavioral;

Gate_VHDL/full_sub/full_sub_tb.vhdl
library ieee;
use ieee.std_logic_1164.all;

entity full_sub_tb is
end full_sub_tb;

architecture behavioral of full_sub_tb is
signal a,b,bin,diff,bo : std_logic;
begin

uut : entity work.full_sub port map(
    a => a,
    b => b,
    bin => bin,
    diff => diff,
    bo => bo
);

stim: 
process begin
a <= '0'; b<='0'; bin<='0'; wait for 10 ns;
a <= '0'; b<='0'; bin<='1'; wait for 10 ns;
a <= '0'; b<='1'; bin<='0'; wait for 10 ns;
a <= '0'; b<='1'; bin<='1'; wait for 10 ns;
a <= '1'; b<='0'; bin<='0'; wait for 10 ns;
a <= '1'; b<='0'; bin<='1'; wait for 10 ns;
a <= '1'; b<='1'; bin<='0'; wait for 10 ns;
a <= '1'; b<='1'; bin<='1'; wait for 10 ns;
wait;
end process;
end behavioral;

Gate_VHDL/full_sub/wave.vcd
$date
  Wed Nov 05 23:20:47 2025
$end
$version
  GHDL v0
$end
$timescale
  1 fs
$end
$scope module standard $end
$upscope $end
$scope module std_logic_1164 $end
$upscope $end
$scope module full_sub_tb $end
$var reg 1 ! a $end
$var reg 1 " b $end
$var reg 1 # bin $end
$var reg 1 $ diff $end
$var reg 1 % bo $end
$scope module uut $end
$var reg 1 & a $end
$var reg 1 ' b $end
$var reg 1 ( bin $end
$var reg 1 ) diff $end
$var reg 1 * bo $end
$upscope $end
$upscope $end
$enddefinitions $end
#0
0!
0"
0#
0$
0%
0&
0'
0(
0)
0*
#10000000
1#
1$
1(
1)
#20000000
1"
0#
1%
1'
0(
1*
#30000000
1#
0$
1(
0)
#40000000
1!
0"
0#
1$
0%
1&
0'
0(
1)
0*
#50000000
1#
0$
1(
0)
#60000000
1"
0#
1'
0(
#70000000
1#
1$
1%
1(
1)
1*
