Gate_Verilog/mileys_model/mileys_model.v
module mileys_module(clk,rst,x,z);
input wire clk,rst,x;
output reg z;

parameter s0=2'b00, s1=2'b01, s2=2'b10;
reg [1:0]next_s,curr_s;
always @(posedge clk or negedge rst)
begin
if (rst == 1'b0) begin
    curr_s <= s0;
end
else begin
    curr_s <= next_s;
end
end
always @(*) begin
    case(curr_s)
        s0 : begin
            z = 1'b0;
            if (x==0) begin
                next_s = s0;
            end
            else begin
                next_s = s1;
            end
        end
        s1 : begin
            z = 1'b0;
            if (x==0) begin 
                next_s = s2;
            end
            else begin
                next_s = s1;
            end
        end
        s2: begin
            z = 1'b1;
            if (x==0) begin
                next_s = s0;
            end
            else begin
                next_s = s1;
            end
        end
    endcase
end
endmodule

Gate_Verilog/mileys_model/mileys_model_tb.v
module mileys_module_tb();
reg clk,rst,x;
wire z;

mileys_module uut(
    .clk(clk),
    .rst(rst),
    .z(z),
    .x(x)
);

initial begin 
clk <= 1'b0;
forever #5
clk <= ~clk;
end

initial begin
$dumpfile("dump.vcd");
$dumpvars(0,mileys_module_tb);
rst<=1'b0;#10;
rst <= 1'b1;
x <= 1'b0;#10;
x <= 1'b1;#10;
x <= 1'b0;#10;
x <= 1'b1;#10;
x <= 1'b1;#10;
#100;
$finish;
end
endmodule

Gate_Verilog/mileys_model/dump.vcd
$date
	Sun Nov 23 23:18:27 2025
$end
$version
	Icarus Verilog
$end
$timescale
	1s
$end
$scope module mileys_module_tb $end
$var wire 1 ! z $end
$var reg 1 " clk $end
$var reg 1 # rst $end
$var reg 1 $ x $end
$scope module uut $end
$var wire 1 " clk $end
$var wire 1 # rst $end
$var wire 1 $ x $end
$var parameter 2 % s0 $end
$var parameter 2 & s1 $end
$var parameter 2 ' s2 $end
$var reg 2 ( curr_s [1:0] $end
$var reg 2 ) next_s [1:0] $end
$var reg 1 ! z $end
$upscope $end
$upscope $end
$enddefinitions $end
$comment Show the parameter values. $end
$dumpall
b10 '
b1 &
b0 %
$end
#0
$dumpvars
b1 )
b0 (
x$
0#
0"
0!
$end
#5
1"
#10
b0 )
0"
0$
1#
#15
1"
#20
b1 )
0"
1$
#25
b1 (
1"
#30
b10 )
0"
0$
#35
b0 )
1!
b10 (
1"
#40
b1 )
0"
1$
#45
0!
b1 (
1"
