Gate_Verilog/moore_model/moore.v
module moore(clk,rst,x,z);
input wire clk,rst,x;
output reg z;
parameter a=2'b00,b=2'b01,c=2'b10,d=2'b11;
reg [1:0]curr_s,next_s;

always @(posedge clk or negedge rst)
begin
    if (rst==1'b0) begin
        z <= 1'b0;
        curr_s <= a;
    end
    else 
        curr_s <= next_s;
end

always @(*) begin
    case (curr_s)
        a : begin
            z <= 1'b0;
            if (x) begin   
                next_s<=b;
            end
        end
        b : begin
            z<= 1'b0;
            if (x) begin
                next_s <= c;
            end
        end
        c : begin
            z <= 1'b0;
            if (x) begin
                next_s <= d;
            end
        end
        d : begin
            z <= 1'b1;
            if (x) begin
              next_s <= b;
            end
            else begin
                next_s <= a;
            end
        end
    endcase
end 
endmodule

Gate_Verilog/moore_model/moore_tb.v
module moore_tb();
reg clk,rst,x;
wire z;

moore uut (
    .clk(clk),
    .rst(rst),
    .x(x),
    .z(z)
);

initial begin
    clk <= 1'b0;
    forever #5
    clk <= ~clk;
end

initial begin
    $dumpfile("dump.vcd");
    $dumpvars(0,moore_tb);
    rst <= 1'b0; #10;
    rst <= 1'b1;
    x <= 1'b1; #10;
    x <= 1'b1; #10;
    x <= 1'b1; #10;
    x <= 1'b0; #10;
    x <= 1'b1; #10;
    $finish;
end
endmodule

Gate_Verilog/moore_model/dump.vcd
$date
	Thu Nov 27 22:24:54 2025
$end
$version
	Icarus Verilog
$end
$timescale
	1s
$end
$scope module moore_tb $end
$var wire 1 ! z $end
$var reg 1 " clk $end
$var reg 1 # rst $end
$var reg 1 $ x $end
$scope module uut $end
$var wire 1 " clk $end
$var wire 1 # rst $end
$var wire 1 $ x $end
$var parameter 2 % a $end
$var parameter 2 & b $end
$var parameter 2 ' c $end
$var parameter 2 ( d $end
$var reg 2 ) curr_s [1:0] $end
$var reg 2 * next_s [1:0] $end
$var reg 1 ! z $end
$upscope $end
$upscope $end
$enddefinitions $end
$comment Show the parameter values. $end
$dumpall
b11 (
b10 '
b1 &
b0 %
$end
#0
$dumpvars
bx *
b0 )
x$
0#
0"
0!
$end
#5
1"
#10
b1 *
0"
1$
1#
#15
b10 *
b1 )
1"
#20
0"
#25
b11 *
b10 )
1"
#30
0"
#35
b1 *
1!
b11 )
1"
#40
b0 *
0"
0$
#45
0!
b0 )
1"
#50
b1 *
0"
1$
#55
b10 *
b1 )
1"
