Gate_VHDL/ring_cnt/ring_cnt.vhdl
library ieee;
use ieee.std_logic_1164.all;
use ieee.numeric_std.all;

entity ring_cnt is
port(
    clk,rst : in std_logic;
    q : out std_logic_vector(3 downto 0)
);
end ring_cnt;

architecture behavioral of ring_cnt is
signal a : std_logic_vector(3 downto 0);
begin
process (clk,rst) begin
if (rst='0') then
    a <= "1001";
elsif (rising_edge(clk)) then
    a <= a(2 downto 0) & a(3);
end if;
end process;
q <= a;
end behavioral;

Gate_VHDL/ring_cnt/ring_cnt_tb.vhdl
library ieee;
use ieee.std_logic_1164.all;
use ieee.numeric_std.all;

entity ring_cnt_tb is
end ring_cnt_tb;

architecture behavioral of ring_cnt_tb is
signal clk,rst: std_logic;
signal q : std_logic_vector(3 downto 0);
begin
uut : entity work.ring_cnt port map(
    clk => clk,
    rst => rst,
    q => q
);

clk_process : process
begin
while true loop 
clk <= '0';
wait for 5 ns;
clk <= not clk;
wait for 5 ns;
end loop;
end process clk_process;

stim: process
begin
rst<='0'; wait for 10 ns;
rst <= '1' ;
wait;
end process;
end behavioral;

Gate_VHDL/ring_cnt/wave.vcd
$date
  Sat Nov 15 23:14:57 2025
$end
$version
  GHDL v0
$end
$timescale
  1 fs
$end
$scope module standard $end
$upscope $end
$scope module std_logic_1164 $end
$upscope $end
$scope module numeric_std $end
$upscope $end
$scope module ring_cnt_tb $end
$var reg 1 ! clk $end
$var reg 1 " rst $end
$var reg 4 # q[3:0] $end
$scope module uut $end
$var reg 1 $ clk $end
$var reg 1 % rst $end
$var reg 4 & q[3:0] $end
$var reg 4 ' a[3:0] $end
$upscope $end
$upscope $end
$enddefinitions $end
#0
0!
0"
b1001 #
0$
0%
b1001 &
b1001 '
#5000000
1!
1$
#10000000
0!
1"
0$
1%
#15000000
1!
b0011 #
1$
b0011 &
b0011 '
#20000000
0!
0$
#25000000
1!
b0110 #
1$
b0110 &
b0110 '
#30000000
0!
0$
#35000000
1!
b1100 #
1$
b1100 &
b1100 '
#40000000
0!
0$
#45000000
1!
b1001 #
1$
b1001 &
b1001 '
#50000000
0!
0$
#55000000
1!
b0011 #
1$
b0011 &
b0011 '
#60000000
0!
0$
#65000000
1!
b0110 #
1$
b0110 &
b0110 '
#70000000
0!
0$
#75000000
1!
b1100 #
1$
b1100 &
b1100 '
#80000000
0!
0$
#85000000
1!
b1001 #
1$
b1001 &
b1001 '
#90000000
0!
0$
#95000000
1!
b0011 #
1$
b0011 &
b0011 '
