Gate_Verilog/full_adder/full_adder.v
module full_adder(a,b,cin,sum,cout);
    input wire a,b,cin;
    output wire sum,cout;

assign cout = (a&b)|(cin&(a^b)) ;
assign sum = a^b^cin;
endmodule

Gate_Verilog/full_adder/full_adder_tb.v
`timescale 1ns/1ps
module full_adder_tb;
    reg a,b,cin;
    wire sum, cout;

full_adder uut (
    .a(a),
    .b(b),
    .cin(cin),
    .sum(sum),
    .cout(cout)
);

initial begin
    $dumpfile("wave.vcd");
    $dumpvars(0,full_adder_tb);

    a=1'b0; b=1'b0; cin=1'b0; #10;
    a=1'b0; b=1'b0; cin=1'b1; #10;
    a=1'b0; b=1'b1; cin=1'b0; #10;
    a=1'b0; b=1'b1; cin=1'b1; #10;
    a=1'b1; b=1'b0; cin=1'b0; #10;
    a=1'b1; b=1'b0; cin=1'b1; #10;
    a=1'b1; b=1'b1; cin=1'b0; #10;
    a=1'b1; b=1'b1; cin=1'b1; #10;
    $finish;
end;    
endmodule

Gate_Verilog/full_adder/wave.vcd
$date
	Tue Nov 04 23:10:57 2025
$end
$version
	Icarus Verilog
$end
$timescale
	1ps
$end
$scope module full_adder_tb $end
$var wire 1 ! sum $end
$var wire 1 " cout $end
$var reg 1 # a $end
$var reg 1 $ b $end
$var reg 1 % cin $end
$scope module uut $end
$var wire 1 # a $end
$var wire 1 $ b $end
$var wire 1 % cin $end
$var wire 1 " cout $end
$var wire 1 ! sum $end
$upscope $end
$upscope $end
$enddefinitions $end
$comment Show the parameter values. $end
$dumpall
$end
#0
$dumpvars
0%
0$
0#
0"
0!
$end
#10000
1!
1%
#20000
0%
1$
#30000
1"
0!
1%
#40000
0"
1!
0%
0$
1#
#50000
1"
0!
1%
#60000
0%
1$
#70000
1!
1%
