Gate_Verilog/tab3/tab3.v
module tab3(clk,rst,index,result);
input wire clk,rst;
output reg[7:0] result;
output reg[3:0] index;

reg [3:0] counter;
always @(posedge clk or negedge rst)
begin
    if (rst==1'b0) begin
        counter <= 7'b0;
        index <= 4'b0;
        result <= 8'b0;
    end
    else if(counter < 11) begin
        counter <=counter+1;
        index <= counter;
        result<=counter*3;
    end
end
endmodule

Gate_Verilog/tab3/tab3_tb.v
module tab3_tb();
wire [7:0] result;
wire [3:0] index;
reg clk,rst;

tab3 uut (
    .clk(clk),
    .rst(rst),
    .result(result),
    .index(index)
);

initial begin 
clk <= 1'b0;
forever #5
clk <= ~clk;
end

initial begin
    $dumpfile("dump.vcd");
    $dumpvars(0,tab3_tb);
    rst <= 1'b0;
    #10;
    rst<=1'b1;
    #200;
    $finish;
end
endmodule

Gate_Verilog/tab3/dump.vcd
$date
	Mon Dec 01 23:43:12 2025
$end
$version
	Icarus Verilog
$end
$timescale
	1s
$end
$scope module tab3_tb $end
$var wire 8 ! result [7:0] $end
$var wire 4 " index [3:0] $end
$var reg 1 # clk $end
$var reg 1 $ rst $end
$scope module uut $end
$var wire 1 # clk $end
$var wire 1 $ rst $end
$var reg 4 % counter [3:0] $end
$var reg 4 & index [3:0] $end
$var reg 8 ' result [7:0] $end
$upscope $end
$upscope $end
$enddefinitions $end
$comment Show the parameter values. $end
$dumpall
$end
#0
$dumpvars
b0 '
b0 &
b0 %
0$
0#
b0 "
b0 !
$end
#5
1#
#10
0#
1$
#15
b1 %
1#
#20
0#
#25
b11 !
b11 '
b1 "
b1 &
b10 %
1#
#30
0#
#35
b110 !
b110 '
b10 "
b10 &
b11 %
1#
#40
0#
#45
b1001 !
b1001 '
b11 "
b11 &
b100 %
1#
#50
0#
#55
b1100 !
b1100 '
b100 "
b100 &
b101 %
1#
#60
0#
#65
b1111 !
b1111 '
b101 "
b101 &
b110 %
1#
#70
0#
#75
b10010 !
b10010 '
b110 "
b110 &
b111 %
1#
#80
0#
#85
b10101 !
b10101 '
b111 "
b111 &
b1000 %
1#
#90
0#
#95
b11000 !
b11000 '
b1000 "
b1000 &
b1001 %
1#
#100
0#
#105
b11011 !
b11011 '
b1001 "
b1001 &
b1010 %
1#
#110
0#
#115
b11110 !
b11110 '
b1010 "
b1010 &
b1011 %
1#
