Gate_VHDL/moore/moore.vhdl
library ieee;
use ieee.std_logic_1164.all;
use ieee.numeric_std.all;

entity moore is
port(
    clk,rst,x : in std_logic;
    z : out std_logic
);
end moore;

architecture behavioral of moore is
type type_state is (a,b,c,d);
signal curr_s,next_s : type_state;
begin
process (clk,rst)
begin
    if (rst='0') then
        z <= '0';
        curr_s <= a; 
    elsif(clk'event and clk='1') then
        curr_s <= next_s;
    end if;
end process;

process (curr_s,x) 
begin
    case curr_s is 
        when a => 
            z <= '0';
            if (x='1') then
                next_s <= b;
            end if;
        when b =>
            z <= '0';
            if (x='1') then
                next_s <= c;
            end if;
        when c =>
            z <= '0';
            if (x='1') then
                next_s <= d;
            end if;
        when d =>
            z <= '1';
            if (x='0') then
                next_s <= a;
            else
                next_s <= b;
            end if;
    end case;
end process;
end behavioral;

Gate_VHDL/moore/moore_tb.vhdl
library ieee;
use ieee.std_logic_1164.all;
use ieee.numeric_std.all;

entity moore_tb is
end moore_tb;

architecture behavioral of moore_tb is
signal clk,rst,x,z : std_logic;
begin
uut : entity work.moore port map(
    clk=>clk,
    rst=>rst,
    x=>x,
    z=>z
);

clk_process :
process begin
while true loop
clk <= '0';
wait for 5 ns;
clk <= not clk;
wait for 5 ns;
end loop;
end process;

stim: process
begin
rst <= '0'; wait for 10 ns;
rst <= '1';
x <= '1'; wait for 10 ns;
x <= '1'; wait for 10 ns;
x <= '1'; wait for 10 ns;
x <= '0'; wait for 10 ns;
x <= '1'; wait for 10 ns;
wait;
end process;
end behavioral;

Gate_VHDL/moore/wave.vcd
$date
  Thu Nov 27 22:54:55 2025
$end
$version
  GHDL v0
$end
$timescale
  1 fs
$end
$scope module standard $end
$upscope $end
$scope module std_logic_1164 $end
$upscope $end
$scope module numeric_std $end
$upscope $end
$scope module moore_tb $end
$var reg 1 ! clk $end
$var reg 1 " rst $end
$var reg 1 # x $end
$var reg 1 $ z $end
$scope module uut $end
$var reg 1 % clk $end
$var reg 1 & rst $end
$var reg 1 ' x $end
$var reg 1 ( z $end
$comment curr_s is not handled $end
$comment next_s is not handled $end
$upscope $end
$upscope $end
$enddefinitions $end
#0
0!
0"
U#
0$
0%
0&
U'
0(
#5000000
1!
1%
0(
#10000000
0!
1"
1#
0%
1&
1'
0(
#15000000
1!
1%
0(
#20000000
0!
0%
#25000000
1!
1%
0(
#30000000
0!
0%
#35000000
1!
X$
1%
X(
#40000000
0!
0#
0%
0'
X(
#45000000
1!
0$
1%
0(
#50000000
0!
1#
0%
1'
0(
#55000000
1!
1%
0(
#60000000
0!
0%
#65000000
1!
1%
0(
#70000000
0!
0%
#75000000
1!
X$
1%
X(
#80000000
0!
0%
#85000000
1!
0$
1%
0(
#90000000
0!
0%
#95000000
1!
1%
0(
#100000000
0!
0%
#105000000
1!
X$
1%
X(
#110000000
0!
0%
#115000000
1!
0$
1%
0(
#120000000
0!
0%
#125000000
1!
1%
0(
#130000000
0!
0%
#135000000
1!
X$
1%
X(
#140000000
0!
0%
#145000000
1!
0$
1%
0(
#150000000
0!
0%
#155000000
1!
1%
0(
#160000000
0!
0%
#165000000
1!
X$
1%
X(
#170000000
0!
0%
#175000000
1!
0$
1%
0(
#180000000
0!
0%
#185000000
1!
1%
0(
#190000000
0!
0%
#195000000
1!
X$
1%
X(
#200000000
0!
0%
#205000000
1!
0$
1%
0(
#210000000
0!
0%
#215000000
1!
1%
0(
#220000000
0!
0%
#225000000
1!
X$
1%
X(
#230000000
0!
0%
#235000000
1!
0$
1%
0(
#240000000
0!
0%
#245000000
1!
1%
0(
#250000000
0!
0%
#255000000
1!
X$
1%
X(
#260000000
0!
0%
#265000000
1!
0$
1%
0(
#270000000
0!
0%
#275000000
1!
1%
0(
#280000000
0!
0%
#285000000
1!
X$
1%
X(
#290000000
0!
0%
#295000000
1!
0$
1%
0(
#300000000
0!
0%
#305000000
1!
1%
0(
#310000000
0!
0%
#315000000
1!
X$
1%
X(
#320000000
0!
0%
#325000000
1!
0$
1%
0(
#330000000
0!
0%
#335000000
1!
1%
0(
#340000000
0!
0%
#345000000
1!
X$
1%
X(
#350000000
0!
0%
#355000000
1!
0$
1%
0(
#360000000
0!
0%
#365000000
1!
1%
0(
#370000000
0!
0%
#375000000
1!
X$
1%
X(
#380000000
0!
0%
#385000000
1!
0$
1%
0(
#390000000
0!
0%
#395000000
1!
1%
0(
#400000000
0!
0%
#405000000
1!
X$
1%
X(
#410000000
0!
0%
#415000000
1!
0$
1%
0(
#420000000
0!
0%
#425000000
1!
1%
0(
#430000000
0!
0%
#435000000
1!
X$
1%
X(
#440000000
0!
0%
#445000000
1!
0$
1%
0(
#450000000
0!
0%
#455000000
1!
1%
0(
#460000000
0!
0%
#465000000
1!
X$
1%
X(
#470000000
0!
0%
#475000000
1!
0$
1%
0(
#480000000
0!
0%
#485000000
1!
1%
0(
#490000000
0!
0%
#495000000
1!
X$
1%
X(
