Gate_Verilog/parcheck/parcheck.v
module parcheck(clk,rst,in,even,odd);
input wire clk,rst;
input wire [8:0]in;
output reg even,odd;

integer i;
reg [3:0]count;

always @(posedge clk or negedge rst) 
begin   
    count <= 4'b0000;
    if (rst == 1'b0) begin
        even <= 1'b0;
        odd <= 1'b0;
        count <= 4'b0000;
    end
    else begin
        for (i=0;i<9;i=i+1) begin
            if (in[i]==1'b1) begin
                count = count+1;
            end
        end
    end
even = (count%2)?1'b1:1'b0;
odd = (count%2)?1'b0:1'b1;
end
endmodule

Gate_Verilog/parcheck/parcheck_tb.v
module parcheck_tb();
reg clk,rst;
reg [8:0]in;
wire even,odd;

parcheck uut(
    .clk(clk),
    .rst(rst),
    .in(in),
    .even(even),
    .odd(odd)
);

initial begin
    clk <= 1'b0;
    forever #5 
    clk <= ~clk;
end 

initial begin
    $dumpfile("dump.vcd");
    $dumpvars(0,parcheck_tb);
    rst <= 1'b0; #10;
    rst <=1'b1;
    in <= 9'b101010111; #10;
    in <= 9'b101110111; #10;
    in <= 9'b100000111; #10;
    in <= 9'b101111011; #10;
    in <= 9'b110000111; #10;
    $finish;
end
endmodule

Gate_Verilog/parcheck/dump.vcd
$date
	Fri Nov 28 23:07:51 2025
$end
$version
	Icarus Verilog
$end
$timescale
	1s
$end
$scope module parcheck_tb $end
$var wire 1 ! odd $end
$var wire 1 " even $end
$var reg 1 # clk $end
$var reg 9 $ in [8:0] $end
$var reg 1 % rst $end
$scope module uut $end
$var wire 1 # clk $end
$var wire 9 & in [8:0] $end
$var wire 1 % rst $end
$var reg 4 ' count [3:0] $end
$var reg 1 " even $end
$var reg 1 ! odd $end
$var integer 32 ( i [31:0] $end
$upscope $end
$upscope $end
$enddefinitions $end
$comment Show the parameter values. $end
$dumpall
$end
#0
$dumpvars
bx (
b0 '
bx &
0%
bx $
0#
0"
0!
$end
#5
0!
1#
#10
0#
b101010111 $
b101010111 &
1%
#15
1!
b0 '
b1001 (
1#
#20
0#
b101110111 $
b101110111 &
#25
0!
1"
b0 '
b1001 (
1#
#30
0#
b100000111 $
b100000111 &
#35
1!
0"
b0 '
b1001 (
1#
#40
0#
b101111011 $
b101111011 &
#45
0!
1"
b0 '
b1001 (
1#
#50
0#
b110000111 $
b110000111 &
#55
b0 '
b1001 (
1#
