Gate_Verilog/sipo/sipo.v
module sipo(clk,rst,sin,sout);
input wire clk,rst;
input wire sin;
output reg[3:0]sout;

always @(posedge clk or negedge rst) 
begin
if (rst==1'b0) begin
    sout <= 4'b0000;
end
else begin
    sout <= {sout[2:0],sin};
end
end
endmodule

Gate_Verilog/sipo/sipo_tb.v
module sipo_tb();
reg clk,rst,sin;
wire [3:0]sout;

sipo uut (
    .clk(clk),
    .rst(rst),
    .sin(sin),
    .sout(sout)
);

initial begin
clk<=1'b0;
forever #5
clk <= ~clk;
end

initial begin
$dumpfile("dump.vcd");
$dumpvars(0,sipo_tb);
rst <= 1'b0; #10;
rst <= 1'b1; sin <= 1'b1; #10;
sin <= 1'b0; #10;
sin <= 1'b0; #10;
sin <= 1'b1; #10;
sin <= 1'b0; #10;
$finish;
end 
endmodule

Gate_Verilog/sipo/dump.vcd
$date
	Thu Nov 20 22:31:09 2025
$end
$version
	Icarus Verilog
$end
$timescale
	1s
$end
$scope module sipo_tb $end
$var wire 4 ! sout [3:0] $end
$var reg 1 " clk $end
$var reg 1 # rst $end
$var reg 1 $ sin $end
$scope module uut $end
$var wire 1 " clk $end
$var wire 1 # rst $end
$var wire 1 $ sin $end
$var reg 4 % sout [3:0] $end
$upscope $end
$upscope $end
$enddefinitions $end
$comment Show the parameter values. $end
$dumpall
$end
#0
$dumpvars
b0 %
x$
0#
0"
b0 !
$end
#5
1"
#10
0"
1$
1#
#15
b1 !
b1 %
1"
#20
0"
0$
#25
b10 !
b10 %
1"
#30
0"
#35
b100 !
b100 %
1"
#40
0"
1$
#45
b1001 !
b1001 %
1"
#50
0"
0$
#55
b10 !
b10 %
1"
