Gate_VHDL/piso/piso.vhdl
library ieee;
use ieee.std_logic_1164.all;
use ieee.numeric_std.all;

entity piso is
port (
    clk,rst : in std_logic;
    sout : out std_logic;
    sin : in std_logic_vector(3 downto 0)
);
end piso;

architecture behavioral of piso is
signal temp : unsigned(3 downto 0);
begin
process(clk,rst) 
begin
if (rst='0') then
    sout <= '0';
    temp <= "0000";
elsif (rising_edge(clk)) then
    if (to_integer(temp) < 4) then
        sout <= sin(to_integer(temp));
        temp <= temp+1;
    else
        temp <= "0000";
    end if;
end if;
end process;
end behavioral;

Gate_VHDL/piso/piso_tb.vhdl
library ieee;
use ieee.std_logic_1164.all;
use ieee.numeric_std.all;

entity piso_tb is
end piso_tb;

architecture behavioral of piso_tb is
signal clk,rst,sout : std_logic;
signal sin : std_logic_vector( 3 downto 0);
begin

uut: entity work.piso port map(
    clk => clk,
    rst => rst,
    sin => sin,
    sout => sout
);

clk_process : process
begin
while true loop
clk <= '0';
wait for 5 ns;
clk <= not clk ;
wait for 5 ns;
end loop;
end process;

stim: process
begin
rst <='0';
wait for 10 ns;
rst <= '1'; 
sin <= "1001";
wait for 400 ns;
wait;
end process;
end behavioral;

Gate_VHDL/piso/wave.vcd
$date
  Sat Nov 22 23:52:51 2025
$end
$version
  GHDL v0
$end
$timescale
  1 fs
$end
$scope module standard $end
$upscope $end
$scope module std_logic_1164 $end
$upscope $end
$scope module numeric_std $end
$upscope $end
$scope module piso_tb $end
$var reg 1 ! clk $end
$var reg 1 " rst $end
$var reg 1 # sout $end
$var reg 4 $ sin[3:0] $end
$scope module uut $end
$var reg 1 % clk $end
$var reg 1 & rst $end
$var reg 1 ' sout $end
$var reg 4 ( sin[3:0] $end
$var reg 4 ) temp[3:0] $end
$upscope $end
$upscope $end
$enddefinitions $end
#0
0!
0"
0#
bUUUU $
0%
0&
0'
bUUUU (
b0000 )
#5000000
1!
1%
#10000000
0!
1"
b1001 $
0%
1&
b1001 (
#15000000
1!
1#
1%
1'
b0001 )
#20000000
0!
0%
#25000000
1!
0#
1%
0'
b0010 )
#30000000
0!
0%
#35000000
1!
1%
b0011 )
#40000000
0!
0%
#45000000
1!
1#
1%
1'
b0100 )
#50000000
0!
0%
#55000000
1!
1%
b0000 )
#60000000
0!
0%
#65000000
1!
1%
b0001 )
#70000000
0!
0%
#75000000
1!
0#
1%
0'
b0010 )
#80000000
0!
0%
#85000000
1!
1%
b0011 )
#90000000
0!
0%
#95000000
1!
1#
1%
1'
b0100 )
#100000000
0!
0%
#105000000
1!
1%
b0000 )
#110000000
0!
0%
#115000000
1!
1%
b0001 )
#120000000
0!
0%
#125000000
1!
0#
1%
0'
b0010 )
#130000000
0!
0%
#135000000
1!
1%
b0011 )
#140000000
0!
0%
#145000000
1!
1#
1%
1'
b0100 )
#150000000
0!
0%
#155000000
1!
1%
b0000 )
#160000000
0!
0%
#165000000
1!
1%
b0001 )
#170000000
0!
0%
#175000000
1!
0#
1%
0'
b0010 )
#180000000
0!
0%
#185000000
1!
1%
b0011 )
#190000000
0!
0%
#195000000
1!
1#
1%
1'
b0100 )
#200000000
0!
0%
#205000000
1!
1%
b0000 )
#210000000
0!
0%
#215000000
1!
1%
b0001 )
#220000000
0!
0%
#225000000
1!
0#
1%
0'
b0010 )
#230000000
0!
0%
#235000000
1!
1%
b0011 )
#240000000
0!
0%
#245000000
1!
1#
1%
1'
b0100 )
#250000000
0!
0%
#255000000
1!
1%
b0000 )
#260000000
0!
0%
#265000000
1!
1%
b0001 )
#270000000
0!
0%
#275000000
1!
0#
1%
0'
b0010 )
#280000000
0!
0%
#285000000
1!
1%
b0011 )
#290000000
0!
0%
#295000000
1!
1#
1%
1'
b0100 )
#300000000
0!
0%
#305000000
1!
1%
b0000 )
#310000000
0!
0%
#315000000
1!
1%
b0001 )
#320000000
0!
0%
#325000000
1!
0#
1%
0'
b0010 )
#330000000
0!
0%
#335000000
1!
1%
b0011 )
#340000000
0!
0%
#345000000
1!
1#
1%
1'
b0100 )
#350000000
0!
0%
#355000000
1!
1%
b0000 )
#360000000
0!
0%
#365000000
1!
1%
b0001 )
#370000000
0!
0%
#375000000
1!
0#
1%
0'
b0010 )
#380000000
0!
0%
#385000000
1!
1%
b0011 )
#390000000
0!
0%
#395000000
1!
1#
1%
1'
b0100 )
#400000000
0!
0%
#405000000
1!
1%
b0000 )
#410000000
0!
0%
#415000000
1!
1%
b0001 )
#420000000
0!
0%
#425000000
1!
0#
1%
0'
b0010 )
#430000000
0!
0%
#435000000
1!
1%
b0011 )
#440000000
0!
0%
#445000000
1!
1#
1%
1'
b0100 )
#450000000
0!
0%
#455000000
1!
1%
b0000 )
#460000000
0!
0%
#465000000
1!
1%
b0001 )
#470000000
0!
0%
#475000000
1!
0#
1%
0'
b0010 )
#480000000
0!
0%
#485000000
1!
1%
b0011 )
#490000000
0!
0%
#495000000
1!
1#
1%
1'
b0100 )
