Gate_Verilog/piso/piso.v
module piso(clk,rst,sin,sout);
input wire clk,rst;
input wire [3:0]sin;
output reg sout;
reg [3:0]temp;
always @(posedge clk or negedge rst) 
begin
if (rst==1'b0) begin
    sout = 1'b0;
    temp = 4'd0;
end
else begin
    sout = sin[temp];
    temp = temp+1;
end
end
endmodule

Gate_Verilog/piso/piso_tb.v
module piso_tb();
reg clk,rst;
wire sout;
reg [3:0]sin;

piso uut (
    .clk(clk),
    .rst(rst),
    .sin(sin),
    .sout(sout)
);

initial begin
    clk <= 1'b0;
    forever #5
    clk <= ~clk;
end

initial begin
$dumpfile("dump.vcd");
$dumpvars(0,piso_tb);
rst <= 1'b0; #10;
rst <= 1'b1; sin <= 4'b1001; 
#400;
$finish;
end
endmodule

Gate_Verilog/piso/dump.vcd
$date
	Sat Nov 22 23:21:02 2025
$end
$version
	Icarus Verilog
$end
$timescale
	1s
$end
$scope module piso_tb $end
$var wire 1 ! sout $end
$var reg 1 " clk $end
$var reg 1 # rst $end
$var reg 4 $ sin [3:0] $end
$scope module uut $end
$var wire 1 " clk $end
$var wire 1 # rst $end
$var wire 4 % sin [3:0] $end
$var reg 1 ! sout $end
$var reg 4 & temp [3:0] $end
$upscope $end
$upscope $end
$enddefinitions $end
$comment Show the parameter values. $end
$dumpall
$end
#0
$dumpvars
b0 &
bx %
bx $
0#
0"
0!
$end
#5
1"
#10
0"
b1001 $
b1001 %
1#
#15
b1 &
1!
1"
#20
0"
#25
b10 &
0!
1"
#30
0"
#35
b11 &
1"
#40
0"
#45
b100 &
1!
1"
#50
0"
#55
b101 &
x!
1"
#60
0"
#65
b110 &
1"
#70
0"
#75
b111 &
1"
#80
0"
#85
b1000 &
1"
#90
0"
#95
b1001 &
1"
#100
0"
#105
b1010 &
1"
#110
0"
#115
b1011 &
1"
#120
0"
#125
b1100 &
1"
#130
0"
#135
b1101 &
1"
#140
0"
#145
b1110 &
1"
#150
0"
#155
b1111 &
1"
#160
0"
#165
b0 &
1"
#170
0"
#175
b1 &
1!
1"
#180
0"
#185
b10 &
0!
1"
#190
0"
#195
b11 &
1"
#200
0"
#205
b100 &
1!
1"
#210
0"
#215
b101 &
x!
1"
#220
0"
#225
b110 &
1"
#230
0"
#235
b111 &
1"
#240
0"
#245
b1000 &
1"
#250
0"
#255
b1001 &
1"
#260
0"
#265
b1010 &
1"
#270
0"
#275
b1011 &
1"
#280
0"
#285
b1100 &
1"
#290
0"
#295
b1101 &
1"
#300
0"
#305
b1110 &
1"
#310
0"
#315
b1111 &
1"
#320
0"
#325
b0 &
1"
#330
0"
#335
b1 &
1!
1"
#340
0"
#345
b10 &
0!
1"
#350
0"
#355
b11 &
1"
#360
0"
#365
b100 &
1!
1"
#370
0"
#375
b101 &
x!
1"
#380
0"
#385
b110 &
1"
#390
0"
#395
b111 &
1"
#400
0"
#405
b1000 &
1"
