Gate_VHDL/down_cnt/down_cnt.vhdl
library ieee;
use ieee.std_logic_1164.all;
use ieee.numeric_std.all;

entity down_cnt is
port(
    clk,rst : in std_logic;
    q : out std_logic_vector(3 downto 0)
);
end down_cnt;

architecture behavioral of down_cnt is
signal a : unsigned(3 downto 0);
begin
process (clk,rst)
begin
if (rst='0') then
    a <= "1111";
elsif (rising_edge(clk)) then
    if (a > "0000") then
        a <= a-1;
    end if;
end if;
end process;
q <= std_logic_vector(a);
end behavioral;

Gate_VHDL/down_cnt/down_cnt_tb.vhdl
library ieee;
use ieee.std_logic_1164.all;
use ieee.numeric_std.all;

entity down_cnt_tb is
end down_cnt_tb;

architecture behavioral of down_cnt_tb is
signal clk,rst : std_logic;
signal q : std_logic_vector(3 downto 0);
begin

uut : entity work.down_cnt port map(
    clk => clk,
    rst => rst,
    q => q
);

clk_process : process
begin
while true loop
clk <= '0';
wait for 5 ns;
clk <= not clk;
wait for 5 ns;
end loop;
end process;

stim : process
begin
rst <= '0'; wait for 10 ns;
rst <= '1'; wait for 400 ns;
wait;
end process;
end behavioral;

Gate_VHDL/down_cnt/wave.vcd
$date
  Wed Nov 19 22:55:47 2025
$end
$version
  GHDL v0
$end
$timescale
  1 fs
$end
$scope module standard $end
$upscope $end
$scope module std_logic_1164 $end
$upscope $end
$scope module numeric_std $end
$upscope $end
$scope module down_cnt_tb $end
$var reg 1 ! clk $end
$var reg 1 " rst $end
$var reg 4 # q[3:0] $end
$scope module uut $end
$var reg 1 $ clk $end
$var reg 1 % rst $end
$var reg 4 & q[3:0] $end
$var reg 4 ' a[3:0] $end
$upscope $end
$upscope $end
$enddefinitions $end
#0
0!
0"
b1111 #
0$
0%
b1111 &
b1111 '
#5000000
1!
1$
#10000000
0!
1"
0$
1%
#15000000
1!
b1110 #
1$
b1110 &
b1110 '
#20000000
0!
0$
#25000000
1!
b1101 #
1$
b1101 &
b1101 '
#30000000
0!
0$
#35000000
1!
b1100 #
1$
b1100 &
b1100 '
#40000000
0!
0$
#45000000
1!
b1011 #
1$
b1011 &
b1011 '
#50000000
0!
0$
#55000000
1!
b1010 #
1$
b1010 &
b1010 '
#60000000
0!
0$
#65000000
1!
b1001 #
1$
b1001 &
b1001 '
#70000000
0!
0$
#75000000
1!
b1000 #
1$
b1000 &
b1000 '
#80000000
0!
0$
#85000000
1!
b0111 #
1$
b0111 &
b0111 '
#90000000
0!
0$
#95000000
1!
b0110 #
1$
b0110 &
b0110 '
#100000000
0!
0$
#105000000
1!
b0101 #
1$
b0101 &
b0101 '
#110000000
0!
0$
#115000000
1!
b0100 #
1$
b0100 &
b0100 '
#120000000
0!
0$
#125000000
1!
b0011 #
1$
b0011 &
b0011 '
#130000000
0!
0$
#135000000
1!
b0010 #
1$
b0010 &
b0010 '
#140000000
0!
0$
#145000000
1!
b0001 #
1$
b0001 &
b0001 '
#150000000
0!
0$
#155000000
1!
b0000 #
1$
b0000 &
b0000 '
