Gate_VHDL/siso/siso.vhdl
library ieee;
use ieee.std_logic_1164.all;
use ieee.numeric_std.all;

entity siso is
port(
    clk,rst : in std_logic;
    sin : in std_logic_vector(3 downto 0);
    sout : out std_logic_vector(3 downto 0)
);
end siso;

architecture behavioral of siso is 
signal temp : std_logic_vector(3 downto 0);
begin
process (clk,rst)
begin
if (rst='0') then
    temp <= sin;
    sout <= "0000";
elsif (rising_edge(clk)) then
    sout <= temp;
    temp <= temp(2 downto 0) & temp(3);
end if;
end process;
end behavioral;

Gate_VHDL/siso/siso_tb.vhdl
library ieee;
use ieee.std_logic_1164.all;
use ieee.numeric_std.all;

entity siso_tb is
end siso_tb;

architecture behavioral of siso_tb is
signal clk,rst  : std_logic;
signal sin,sout : std_logic_vector(3 downto 0);
begin

uut: entity work.siso port map(
    clk => clk,
    rst => rst,
    sin => sin,
    sout => sout
);

clk_process: process
begin
while true loop
clk <= '0';
wait for 5 ns;
clk <= not clk;
wait for 5 ns;
end loop;
end process;

stim: process
begin
rst <= '0'; sin <="1100";
wait for 10 ns;
rst <='1';
wait for 400 ns;
wait;
end process;
end behavioral;

Gate_VHDL/siso/wave.vcd
$date
  Wed Nov 19 23:41:19 2025
$end
$version
  GHDL v0
$end
$timescale
  1 fs
$end
$scope module standard $end
$upscope $end
$scope module std_logic_1164 $end
$upscope $end
$scope module numeric_std $end
$upscope $end
$scope module siso_tb $end
$var reg 1 ! clk $end
$var reg 1 " rst $end
$var reg 4 # sin[3:0] $end
$var reg 4 $ sout[3:0] $end
$scope module uut $end
$var reg 1 % clk $end
$var reg 1 & rst $end
$var reg 4 ' sin[3:0] $end
$var reg 4 ( sout[3:0] $end
$var reg 4 ) temp[3:0] $end
$upscope $end
$upscope $end
$enddefinitions $end
#0
0!
0"
b1100 #
b0000 $
0%
0&
b1100 '
b0000 (
b1100 )
#5000000
1!
1%
#10000000
0!
1"
0%
1&
#15000000
1!
b1100 $
1%
b1100 (
b1001 )
#20000000
0!
0%
#25000000
1!
b1001 $
1%
b1001 (
b0011 )
#30000000
0!
0%
#35000000
1!
b0011 $
1%
b0011 (
b0110 )
#40000000
0!
0%
#45000000
1!
b0110 $
1%
b0110 (
b1100 )
#50000000
0!
0%
#55000000
1!
b1100 $
1%
b1100 (
b1001 )
#60000000
0!
0%
#65000000
1!
b1001 $
1%
b1001 (
b0011 )
#70000000
0!
0%
#75000000
1!
b0011 $
1%
b0011 (
b0110 )
#80000000
0!
0%
#85000000
1!
b0110 $
1%
b0110 (
b1100 )
#90000000
0!
0%
#95000000
1!
b1100 $
1%
b1100 (
b1001 )
#100000000
0!
0%
#105000000
1!
b1001 $
1%
b1001 (
b0011 )
#110000000
0!
0%
#115000000
1!
b0011 $
1%
b0011 (
b0110 )
#120000000
0!
0%
#125000000
1!
b0110 $
1%
b0110 (
b1100 )
#130000000
0!
0%
#135000000
1!
b1100 $
1%
b1100 (
b1001 )
#140000000
0!
0%
#145000000
1!
b1001 $
1%
b1001 (
b0011 )
#150000000
0!
0%
#155000000
1!
b0011 $
1%
b0011 (
b0110 )
#160000000
0!
0%
#165000000
1!
b0110 $
1%
b0110 (
b1100 )
#170000000
0!
0%
#175000000
1!
b1100 $
1%
b1100 (
b1001 )
#180000000
0!
0%
#185000000
1!
b1001 $
1%
b1001 (
b0011 )
#190000000
0!
0%
#195000000
1!
b0011 $
1%
b0011 (
b0110 )
#200000000
0!
0%
#205000000
1!
b0110 $
1%
b0110 (
b1100 )
#210000000
0!
0%
#215000000
1!
b1100 $
1%
b1100 (
b1001 )
#220000000
0!
0%
#225000000
1!
b1001 $
1%
b1001 (
b0011 )
#230000000
0!
0%
#235000000
1!
b0011 $
1%
b0011 (
b0110 )
#240000000
0!
0%
#245000000
1!
b0110 $
1%
b0110 (
b1100 )
#250000000
0!
0%
#255000000
1!
b1100 $
1%
b1100 (
b1001 )
#260000000
0!
0%
#265000000
1!
b1001 $
1%
b1001 (
b0011 )
#270000000
0!
0%
#275000000
1!
b0011 $
1%
b0011 (
b0110 )
#280000000
0!
0%
#285000000
1!
b0110 $
1%
b0110 (
b1100 )
#290000000
0!
0%
#295000000
1!
b1100 $
1%
b1100 (
b1001 )
#300000000
0!
0%
#305000000
1!
b1001 $
1%
b1001 (
b0011 )
#310000000
0!
0%
#315000000
1!
b0011 $
1%
b0011 (
b0110 )
#320000000
0!
0%
#325000000
1!
b0110 $
1%
b0110 (
b1100 )
#330000000
0!
0%
#335000000
1!
b1100 $
1%
b1100 (
b1001 )
#340000000
0!
0%
#345000000
1!
b1001 $
1%
b1001 (
b0011 )
#350000000
0!
0%
#355000000
1!
b0011 $
1%
b0011 (
b0110 )
#360000000
0!
0%
#365000000
1!
b0110 $
1%
b0110 (
b1100 )
#370000000
0!
0%
#375000000
1!
b1100 $
1%
b1100 (
b1001 )
#380000000
0!
0%
#385000000
1!
b1001 $
1%
b1001 (
b0011 )
#390000000
0!
0%
#395000000
1!
b0011 $
1%
b0011 (
b0110 )
#400000000
0!
0%
#405000000
1!
b0110 $
1%
b0110 (
b1100 )
#410000000
0!
0%
#415000000
1!
b1100 $
1%
b1100 (
b1001 )
#420000000
0!
0%
#425000000
1!
b1001 $
1%
b1001 (
b0011 )
#430000000
0!
0%
#435000000
1!
b0011 $
1%
b0011 (
b0110 )
#440000000
0!
0%
#445000000
1!
b0110 $
1%
b0110 (
b1100 )
#450000000
0!
0%
#455000000
1!
b1100 $
1%
b1100 (
b1001 )
#460000000
0!
0%
#465000000
1!
b1001 $
1%
b1001 (
b0011 )
#470000000
0!
0%
#475000000
1!
b0011 $
1%
b0011 (
b0110 )
#480000000
0!
0%
#485000000
1!
b0110 $
1%
b0110 (
b1100 )
#490000000
0!
0%
#495000000
1!
b1100 $
1%
b1100 (
b1001 )
