Gate_Verilog/full_sub/full_sub.v
module full_sub(a,b,bin,diff,bo);
    input wire a,b,bin;
    output wire bo,diff;

assign diff = a^b^bin;
assign bo = ((~a)&b)|(((~a)|b)&bin);
endmodule

Gate_Verilog/full_sub/full_sub_tb.v
`timescale 1ns/1ps

module full_sub_tb;
    reg a,b,bin;
    wire bo,diff ;

full_sub uut (
    .a(a),
    .b(b),
    .bin(bin),
    .diff(diff),
    .bo(bo)
    );


initial begin
    $dumpfile("wave.vcd");
    $dumpvars(0,full_sub_tb);

    a=1'b0; b=1'b0; bin=1'b0; #10;
    a=1'b0; b=1'b0; bin=1'b1; #10;
    a=1'b0; b=1'b1; bin=1'b0; #10;
    a=1'b0; b=1'b1; bin=1'b1; #10;
    a=1'b1; b=1'b0; bin=1'b0; #10;
    a=1'b1; b=1'b0; bin=1'b1; #10;
    a=1'b1; b=1'b1; bin=1'b0; #10;
    a=1'b1; b=1'b1; bin=1'b1; #10;
    $finish;
end;    

endmodule

Gate_Verilog/full_sub/wave.vcd
$date
	Wed Nov 05 22:59:48 2025
$end
$version
	Icarus Verilog
$end
$timescale
	1ps
$end
$scope module full_sub_tb $end
$var wire 1 ! diff $end
$var wire 1 " bo $end
$var reg 1 # a $end
$var reg 1 $ b $end
$var reg 1 % bin $end
$scope module uut $end
$var wire 1 # a $end
$var wire 1 $ b $end
$var wire 1 % bin $end
$var wire 1 " bo $end
$var wire 1 ! diff $end
$upscope $end
$upscope $end
$enddefinitions $end
$comment Show the parameter values. $end
$dumpall
$end
#0
$dumpvars
0%
0$
0#
0"
0!
$end
#10000
1"
1!
1%
#20000
0%
1$
#30000
0!
1%
#40000
0"
1!
0%
0$
1#
#50000
0!
1%
#60000
0%
1$
#70000
1"
1!
1%
