Gate_VHDL/sipo/sipo.vhdl
library ieee;
use ieee.std_logic_1164.all;
use ieee.numeric_std.all;

entity sipo is
port(
    clk,rst,sin : in std_logic;
    sout : out std_logic_vector(3 downto 0)
);
end sipo;

architecture behavioral of sipo is
signal temp : std_logic_vector(3 downto 0);
begin
process (clk,rst)
begin
if (rst='0') then
    temp <= "0000";
elsif (rising_edge(clk)) then
    temp <= temp(2 downto 0) & sin;
end if;
end process;
sout <= std_logic_vector(temp);
end behavioral;

Gate_VHDL/sipo/sipo_tb.vhdl
library ieee;
use ieee.std_logic_1164.all;
use ieee.numeric_std.all;

entity sipo_tb is
end sipo_tb;

architecture behavioral of sipo_tb is
signal clk,rst,sin : std_logic;
signal sout : std_logic_vector(3 downto 0);
begin
uut : entity work.sipo port map(
    clk => clk,
    rst => rst,
    sin => sin,
    sout => sout
);

clk_process : process
begin
while true loop
clk <= '0';
wait for 5 ns;
clk <= not clk;
wait for 5 ns;
end loop;
end process;

stim: process
begin
rst <= '0' ; wait for 10 ns;
rst <= '1' ; 
sin <= '1'; wait for 10 ns;
sin <= '0'; wait for 10 ns;
sin <= '0'; wait for 10 ns;
sin <= '1'; wait for 10 ns;
sin <= '1'; wait for 10 ns;
wait;
end process;
end behavioral;

Gate_VHDL/sipo/wave.vcd
$date
  Thu Nov 20 22:57:02 2025
$end
$version
  GHDL v0
$end
$timescale
  1 fs
$end
$scope module standard $end
$upscope $end
$scope module std_logic_1164 $end
$upscope $end
$scope module numeric_std $end
$upscope $end
$scope module sipo_tb $end
$var reg 1 ! clk $end
$var reg 1 " rst $end
$var reg 1 # sin $end
$var reg 4 $ sout[3:0] $end
$scope module uut $end
$var reg 1 % clk $end
$var reg 1 & rst $end
$var reg 1 ' sin $end
$var reg 4 ( sout[3:0] $end
$var reg 4 ) temp[3:0] $end
$upscope $end
$upscope $end
$enddefinitions $end
#0
0!
0"
U#
b0000 $
0%
0&
U'
b0000 (
b0000 )
#5000000
1!
1%
#10000000
0!
1"
1#
0%
1&
1'
#15000000
1!
b0001 $
1%
b0001 (
b0001 )
#20000000
0!
0#
0%
0'
#25000000
1!
b0010 $
1%
b0010 (
b0010 )
#30000000
0!
0%
#35000000
1!
b0100 $
1%
b0100 (
b0100 )
#40000000
0!
1#
0%
1'
#45000000
1!
b1001 $
1%
b1001 (
b1001 )
#50000000
0!
0%
#55000000
1!
b0011 $
1%
b0011 (
b0011 )
#60000000
0!
0%
#65000000
1!
b0111 $
1%
b0111 (
b0111 )
#70000000
0!
0%
#75000000
1!
b1111 $
1%
b1111 (
b1111 )
