Gate_Verilog/up_cnt/up_cnt.v
module up_cnt(clk,rst,q);
input wire clk,rst;
output reg [3:0]q;
reg [3:0]a;

always @(posedge clk or negedge rst)
begin
if (rst==1'b0) begin
    a <= 4'd0;
    q <= a;
end
else begin
    if (a < 4'd15) begin
        a <= a + 1;
        q <= a;
    end
    else begin
        a <= 4'd0;
        q <= a;
    end
end
end
endmodule

Gate_Verilog/up_cnt/up_cnt_tb.v
module up_cnt_tb();
reg clk,rst;
wire [3:0]q;

up_cnt uut(
    .clk(clk),
    .rst(rst),
    .q(q)
);

initial begin
    clk = 1'b0;
    forever #5
    clk = ~clk;
end

initial begin
    $dumpfile("dump.vcd");
    $dumpvars(0,up_cnt_tb);
    rst <= 1'b0; #10;
    rst <= 1'b1;#400;
    $finish;
end
endmodule

Gate_Verilog/up_cnt/dump.vcd
$date
	Sun Nov 16 23:36:36 2025
$end
$version
	Icarus Verilog
$end
$timescale
	1s
$end
$scope module up_cnt_tb $end
$var wire 4 ! q [3:0] $end
$var reg 1 " clk $end
$var reg 1 # rst $end
$scope module uut $end
$var wire 1 " clk $end
$var wire 1 # rst $end
$var reg 4 $ a [3:0] $end
$var reg 4 % q [3:0] $end
$upscope $end
$upscope $end
$enddefinitions $end
$comment Show the parameter values. $end
$dumpall
$end
#0
$dumpvars
bx %
b0 $
0#
0"
bx !
$end
#5
b0 !
b0 %
1"
#10
1#
0"
#15
b1 $
1"
#20
0"
#25
b1 !
b1 %
b10 $
1"
#30
0"
#35
b10 !
b10 %
b11 $
1"
#40
0"
#45
b11 !
b11 %
b100 $
1"
#50
0"
#55
b100 !
b100 %
b101 $
1"
#60
0"
#65
b101 !
b101 %
b110 $
1"
#70
0"
#75
b110 !
b110 %
b111 $
1"
#80
0"
#85
b111 !
b111 %
b1000 $
1"
#90
0"
#95
b1000 !
b1000 %
b1001 $
1"
#100
0"
#105
b1001 !
b1001 %
b1010 $
1"
#110
0"
#115
b1010 !
b1010 %
b1011 $
1"
#120
0"
#125
b1011 !
b1011 %
b1100 $
1"
#130
0"
#135
b1100 !
b1100 %
b1101 $
1"
#140
0"
#145
b1101 !
b1101 %
b1110 $
1"
#150
0"
#155
b1110 !
b1110 %
b1111 $
1"
#160
0"
#165
b1111 !
b1111 %
b0 $
1"
#170
0"
#175
b0 !
b0 %
b1 $
1"
#180
0"
#185
b1 !
b1 %
b10 $
1"
#190
0"
#195
b10 !
b10 %
b11 $
1"
#200
0"
#205
b11 !
b11 %
b100 $
1"
#210
0"
#215
b100 !
b100 %
b101 $
1"
#220
0"
#225
b101 !
b101 %
b110 $
1"
#230
0"
#235
b110 !
b110 %
b111 $
1"
#240
0"
#245
b111 !
b111 %
b1000 $
1"
#250
0"
#255
b1000 !
b1000 %
b1001 $
1"
#260
0"
#265
b1001 !
b1001 %
b1010 $
1"
#270
0"
#275
b1010 !
b1010 %
b1011 $
1"
#280
0"
#285
b1011 !
b1011 %
b1100 $
1"
#290
0"
#295
b1100 !
b1100 %
b1101 $
1"
#300
0"
#305
b1101 !
b1101 %
b1110 $
1"
#310
0"
#315
b1110 !
b1110 %
b1111 $
1"
#320
0"
#325
b1111 !
b1111 %
b0 $
1"
#330
0"
#335
b0 !
b0 %
b1 $
1"
#340
0"
#345
b1 !
b1 %
b10 $
1"
#350
0"
#355
b10 !
b10 %
b11 $
1"
#360
0"
#365
b11 !
b11 %
b100 $
1"
#370
0"
#375
b100 !
b100 %
b101 $
1"
#380
0"
#385
b101 !
b101 %
b110 $
1"
#390
0"
#395
b110 !
b110 %
b111 $
1"
#400
0"
#405
b111 !
b111 %
b1000 $
1"
