Gate_Verilog/jh_cnt/jh_cnt.v
module jh_cnt(clk,rst,q);
input wire clk,rst;
output reg [3:0]q;

reg [3:0]a;

always @(posedge clk or negedge rst)
begin
if (rst==0) begin
    a <= 1001;
    q <= a;
end
else begin
    a <= {a[2:0],~a[3]};
    q <= a;
end
end
endmodule

Gate_Verilog/jh_cnt/jh_cnt_tb.v
module jh_cnt_tb();
reg clk,rst;
wire [3:0]q;

jh_cnt uut(
    .clk(clk),
    .rst(rst),
    .q(q)
);

initial begin
clk = 1'b0;
forever #5 
clk = ~ clk;
end

initial begin
$dumpfile("dump.vcd");
$dumpvars(0,jh_cnt_tb);
rst <= 1'b0; #10;
rst <= 1'b1; #100;
$finish;
end 
endmodule

Gate_Verilog/jh_cnt/jh_cnt.vcd
$date
	Sun Nov 16 22:50:12 2025
$end
$version
	Icarus Verilog
$end
$timescale
	1s
$end
$scope module jh_cnt_tb $end
$var wire 4 ! q [3:0] $end
$var reg 1 " clk $end
$var reg 1 # rst $end
$scope module uut $end
$var wire 1 " clk $end
$var wire 1 # rst $end
$var reg 4 $ a [3:0] $end
$var reg 4 % q [3:0] $end
$upscope $end
$upscope $end
$enddefinitions $end
$comment Show the parameter values. $end
$dumpall
$end
#0
$dumpvars
bx %
b1001 $
0#
0"
bx !
$end
#5
b1001 !
b1001 %
1"
#10
1#
0"
#15
b10 $
1"
#20
0"
#25
b10 !
b10 %
b101 $
1"
#30
0"
#35
b101 !
b101 %
b1011 $
1"
#40
0"
#45
b1011 !
b1011 %
b110 $
1"
#50
0"
#55
b110 !
b110 %
b1101 $
1"
#60
0"
#65
b1101 !
b1101 %
b1010 $
1"
#70
0"
#75
b1010 !
b1010 %
b100 $
1"
#80
0"
#85
b100 !
b100 %
b1001 $
1"
#90
0"
#95
b1001 !
b1001 %
b10 $
1"
#100
0"
#105
b10 !
b10 %
b101 $
1"
