Gate_Verilog/SR_FF/sr_ff.v
module sr_ff(clk,rst,s,r,q,qb);
input wire clk,rst,s,r;
output reg q;
output wire qb;

always @(posedge clk or negedge rst)
begin  
    if (rst == 0) begin
        q = 1'b0;
    end
    else begin
        case ({s,r}) 
            2'b00 : q <= q;
            2'b01 : q <= 1'b0;
            2'b10 : q <= 1'b1;
            2'b11 : q <= 1'bx;
        endcase
    end
end  
assign qb = ~ q;
endmodule

Gate_Verilog/SR_FF/sr_ff_tb.v
`timescale 1ns/1ps
module sr_ff_tb();
reg clk, rst, s, r;
wire q;
wire qb;

sr_ff uut(
    .clk(clk),
    .rst(rst),
    .s(s),
    .r(r),
    .q(q),
    .qb(qb)
);

// Clock generation
initial begin
    clk = 0;
    forever #5 clk = ~clk;  // 10ns period clock
end

// Test stimulus
initial begin
    $dumpfile("dump.vcd");
    $dumpvars(0, sr_ff_tb);

    rst = 1'b0;
    s = 0; r = 0;
    #20;

    rst = 1'b1;
    s = 1'b0; r = 1'b0; #10;
    s = 1'b1; r = 1'b0; #10;
    s = 1'b0; r = 1'b1; #10;
    s = 1'b1; r = 1'b1; #10;
    $finish;
end
endmodule

Gate_Verilog/SR_FF/dump.vcd
$date
	Thu Nov 13 23:27:46 2025
$end
$version
	Icarus Verilog
$end
$timescale
	1ps
$end
$scope module sr_ff_tb $end
$var wire 1 ! qb $end
$var wire 1 " q $end
$var reg 1 # clk $end
$var reg 1 $ r $end
$var reg 1 % rst $end
$var reg 1 & s $end
$scope module uut $end
$var wire 1 # clk $end
$var wire 1 ! qb $end
$var wire 1 $ r $end
$var wire 1 % rst $end
$var wire 1 & s $end
$var reg 1 " q $end
$upscope $end
$upscope $end
$enddefinitions $end
$comment Show the parameter values. $end
$dumpall
$end
#0
$dumpvars
0&
0%
0$
0#
0"
1!
$end
#5000
1#
#10000
0#
#15000
1#
#20000
0#
1%
#25000
1#
#30000
0#
1&
#35000
0!
1"
1#
#40000
0#
1$
0&
#45000
1!
0"
1#
#50000
0#
1&
#55000
x!
x"
1#
